resonaate/__init__.py
resonaate/__main__.py
resonaate/agents/__init__.py
resonaate/agents/agent_base.py
resonaate/agents/estimate_agent.py
resonaate/agents/sensing_agent.py
resonaate/agents/target_agent.py
resonaate/common/__init__.py
resonaate/common/behavioral_config.py
resonaate/common/cli.py
resonaate/common/default_behavior.config
resonaate/common/exceptions.py
resonaate/common/labels.py
resonaate/common/logger.py
resonaate/common/utilities.py
resonaate/data/__init__.py
resonaate/data/agent.py
resonaate/data/data_interface.py
resonaate/data/db_connection.py
resonaate/data/detected_maneuver.py
resonaate/data/ephemeris.py
resonaate/data/epoch.py
resonaate/data/filter_step.py
resonaate/data/importer_database.py
resonaate/data/observation.py
resonaate/data/queries.py
resonaate/data/query_util.py
resonaate/data/resonaate_database.py
resonaate/data/table_base.py
resonaate/data/task.py
resonaate/data/events/__init__.py
resonaate/data/events/agent_removal.py
resonaate/data/events/base.py
resonaate/data/events/finite_burn.py
resonaate/data/events/finite_maneuver.py
resonaate/data/events/scheduled_impulse.py
resonaate/data/events/sensor_addition.py
resonaate/data/events/sensor_time_bias.py
resonaate/data/events/target_addition.py
resonaate/data/events/target_task_priority.py
resonaate/dynamics/__init__.py
resonaate/dynamics/celestial.py
resonaate/dynamics/dynamics_base.py
resonaate/dynamics/importer.py
resonaate/dynamics/special_perturbations.py
resonaate/dynamics/terrestrial.py
resonaate/dynamics/two_body.py
resonaate/dynamics/integration_events/__init__.py
resonaate/dynamics/integration_events/continuous_state_change_event.py
resonaate/dynamics/integration_events/discrete_state_change_event.py
resonaate/dynamics/integration_events/event_stack.py
resonaate/dynamics/integration_events/finite_thrust.py
resonaate/dynamics/integration_events/scheduled_impulse.py
resonaate/dynamics/integration_events/station_keeping.py
resonaate/estimation/__init__.py
resonaate-4.1.0.dist-info/licenses/LICENSE
resonaate-4.1.0.dist-info/METADATA
resonaate-4.1.0.dist-info/WHEEL
resonaate-4.1.0.dist-info/entry_points.txt
resonaate-4.1.0.dist-info/top_level.txt
resonaate-4.1.0.dist-info/RECORD
