Metadata-Version: 2.4
Name: resonaate
Version: 4.1.0
Summary: The Responsive Space Observation Analysis and Autonomous Tasking Engine (RESONAATE)
Author-email: "Dr. Kevin Schroeder" <kschro1@vt.edu>, David Kusterer <kdavid13@vt.edu>, Monty Campbell <mcampbell02@vt.edu>, Collin Phillips <ccp1024@vt.edu>, Dylan Thomas <dylan.thomas@vt.edu>, Jon Kadan <jkadan@vt.edu>, Cameron Harris <camerondh@vt.edu>, Connor Segal <csegal@vt.edu>
License-Expression: Apache-2.0
Keywords: space,awareness,astrodynamics,autonomy
Classifier: Development Status :: 5 - Production/Stable
Classifier: Environment :: Console
Classifier: Intended Audience :: Science/Research
Classifier: Topic :: Scientific/Engineering :: Physics
Classifier: Operating System :: Microsoft :: Windows
Classifier: Operating System :: POSIX
Classifier: Programming Language :: Python :: 3.9
Classifier: Programming Language :: Python :: 3.10
Classifier: Programming Language :: Python :: 3.11
Classifier: Programming Language :: Python :: 3.12
Classifier: Programming Language :: Python :: 3.13
Requires-Python: >=3.9
License-File: LICENSE
Requires-Dist: numpy>=1.19
Requires-Dist: scipy>=1.6
Requires-Dist: sqlalchemy>=1.3
Requires-Dist: sgp4==2.23
Requires-Dist: pydantic==2.10.5
Requires-Dist: ray==2.43
Provides-Extra: dev
Requires-Dist: ruff==0.6.4; extra == "dev"
Requires-Dist: mypy==1.11.2; extra == "dev"
Requires-Dist: types-sqlalchemy==1.4.53.38; extra == "dev"
Requires-Dist: black==24.8.0; extra == "dev"
Requires-Dist: isort[colors]==5.13.2; extra == "dev"
Requires-Dist: mdformat==0.7.17; extra == "dev"
Requires-Dist: mdformat-gfm==0.3.6; extra == "dev"
Requires-Dist: pre-commit==3.8.0; extra == "dev"
Requires-Dist: check-manifest==0.49; extra == "dev"
Provides-Extra: doc
Requires-Dist: sphinx==7.4.7; extra == "doc"
Requires-Dist: sphinx_rtd_theme==2.0.0; extra == "doc"
Requires-Dist: matplotlib>=3.3; extra == "doc"
Requires-Dist: myst-parser==3.0.1; extra == "doc"
Requires-Dist: sphinx-copybutton==0.5.1; extra == "doc"
Requires-Dist: sphinxcontrib-bibtex==2.6.2; extra == "doc"
Requires-Dist: sphinxcontrib-mermaid==0.8.1; extra == "doc"
Requires-Dist: sphinx-gallery==0.17.1; extra == "doc"
Requires-Dist: autodoc_pydantic==2.2.0; extra == "doc"
Requires-Dist: importlib-metadata==8.0.0; python_version < "3.10" and extra == "doc"
Provides-Extra: test
Requires-Dist: pytest==8.3.2; extra == "test"
Requires-Dist: pytest-datafiles==3.0.0; extra == "test"
Requires-Dist: pytest-randomly==3.15.0; extra == "test"
Requires-Dist: coverage[toml]==7.6.1; python_version < "3.11" and extra == "test"
Requires-Dist: coverage==7.6.1; python_version >= "3.11" and extra == "test"
Requires-Dist: pytest-cov==5.0.0; extra == "test"
Dynamic: license-file
